neuropycon_data/__init__.py
neuropycon_data/data/__init__.py
neuropycon_data/data/data_con/ROI_MNI_coords-Atlas.txt
neuropycon_data/data/data_con/ROI_labels-Atlas.txt
neuropycon_data/data/data_con/Z_cor_mat_resid_ts.npy
neuropycon_data/data/data_con/__init__.py
neuropycon_data/data/data_con/data_graph/Z_List-info_degrees.txt
neuropycon_data/data/data_con/data_graph/Z_List-info_dists.txt
neuropycon_data/data/data_con/data_graph/Z_List-info_edges_betw.net
neuropycon_data/data/data_con/data_graph/Z_List-info_global.txt
neuropycon_data/data/data_con/data_graph/Z_List-info_nodes.txt
neuropycon_data/data/data_con/data_graph/Z_List.lol
neuropycon_data/data/data_con/data_graph/Z_List.net
neuropycon_data/data/data_con/data_graph/Z_List.txt
neuropycon_data/data/data_con/data_graph/__init__.py
neuropycon_data/data/data_con/data_graph/all_Z_com_degree.txt
neuropycon_data/data/data_con/data_graph/all_participation_coeff.txt
neuropycon_data/data/data_con/data_graph/node_roles.txt
neuropycon_data/data/data_nii/__init__.py
neuropycon_data/data/data_nii/sub-test_mask-anatCSF.nii
neuropycon_data/data/data_nii/sub-test_mask-anatGM.nii
neuropycon_data/data/data_nii/sub-test_mask-anatWM.nii
neuropycon_data/data/data_nii/sub-test_task-rs_bold.nii
neuropycon_data/data/data_nii/Atlas/ROI_MNI_coords-Atlas.txt
neuropycon_data/data/data_nii/Atlas/ROI_coords-Atlas.txt
neuropycon_data/data/data_nii/Atlas/ROI_labels-Atlas.txt
neuropycon_data/data/data_nii/Atlas/__init__.py
neuropycon_data/data/data_nii/Atlas/indexed_mask-Atlas.nii
neuropycon_data-0.0.dev6.dist-info/METADATA
neuropycon_data-0.0.dev6.dist-info/RECORD
neuropycon_data-0.0.dev6.dist-info/WHEEL
neuropycon_data-0.0.dev6.dist-info/top_level.txt
