Metadata-Version: 2.1
Name: neuropycon-data
Version: 0.0.dev6
Summary: Data for neuropycon testing
Home-page: UNKNOWN
Author: David Meunier
Author-email: UNKNOWN
License: UNKNOWN
Platform: UNKNOWN
